geometric_clustering/__init__.py
geometric_clustering/clustering.py
geometric_clustering/curvature.py
geometric_clustering/io.py
geometric_clustering/plotting.py
geometric_clustering-1.0.dist-info/METADATA
geometric_clustering-1.0.dist-info/WHEEL
geometric_clustering-1.0.dist-info/top_level.txt
geometric_clustering-1.0.dist-info/RECORD
